tgcrypto.cp310-win_arm64.pyd
tests/__init__.py
tests/cbc/__init__.py
tests/cbc/test_cbc.py
tests/ctr/__init__.py
tests/ctr/test_ctr.py
tests/ige/__init__.py
tests/ige/test_ige.py
tgcrypto_pyrofork-1.2.8.dist-info/licenses/COPYING
tgcrypto_pyrofork-1.2.8.dist-info/licenses/COPYING.lesser
tgcrypto_pyrofork-1.2.8.dist-info/licenses/NOTICE
tgcrypto_pyrofork-1.2.8.dist-info/METADATA
tgcrypto_pyrofork-1.2.8.dist-info/WHEEL
tgcrypto_pyrofork-1.2.8.dist-info/top_level.txt
tgcrypto_pyrofork-1.2.8.dist-info/RECORD
