Metadata-Version: 2.4
Name: TgCrypto-pyrofork
Version: 1.2.8
Summary: Fast and Portable Cryptography Extension Library for Pyrofork
Home-page: https://github.com/Mayuri-Chan
Download-URL: https://github.com/Mayuri-Chan/tgcrypto/releases/latest
Author: wulan17
Author-email: mayuri@mayuri.my.id
License: LGPLv3+
Project-URL: Tracker, https://github.com/Mayuri-Chan/tgcrypto/issues
Project-URL: Community, https://t.me/MayuriChan_Chat
Project-URL: Source, https://github.com/Mayuri-Chan/tgcrypto
Project-URL: Documentation, https://pyrofork.mayuri.my.id
Keywords: pyrogram pyrofork telegram crypto cryptography encryption mtproto extension library aes
Classifier: Development Status :: 5 - Production/Stable
Classifier: Intended Audience :: Developers
Classifier: License :: OSI Approved :: GNU Lesser General Public License v3 or later (LGPLv3+)
Classifier: Operating System :: OS Independent
Classifier: Programming Language :: C
Classifier: Programming Language :: Python
Classifier: Programming Language :: Python :: 3
Classifier: Programming Language :: Python :: 3.10
Classifier: Programming Language :: Python :: 3.11
Classifier: Programming Language :: Python :: 3.12
Classifier: Programming Language :: Python :: 3.13
Classifier: Programming Language :: Python :: 3.14
Classifier: Programming Language :: Python :: Implementation
Classifier: Programming Language :: Python :: Implementation :: CPython
Classifier: Programming Language :: Python :: Implementation :: PyPy
Classifier: Topic :: Security
Classifier: Topic :: Security :: Cryptography
Classifier: Topic :: Internet
Classifier: Topic :: Communications
Classifier: Topic :: Communications :: Chat
Classifier: Topic :: Software Development :: Libraries
Classifier: Topic :: Software Development :: Libraries :: Python Modules
Requires-Python: ~=3.10
License-File: COPYING
License-File: COPYING.lesser
License-File: NOTICE
Dynamic: author
Dynamic: author-email
Dynamic: classifier
Dynamic: description
Dynamic: description-content-type
Dynamic: download-url
Dynamic: home-page
Dynamic: keywords
Dynamic: license
Dynamic: license-file
Dynamic: project-url
Dynamic: requires-python
Dynamic: summary
